odoo/addons/delivery_automatic_package/README.rst
odoo/addons/delivery_automatic_package/__init__.py
odoo/addons/delivery_automatic_package/__manifest__.py
odoo/addons/delivery_automatic_package/i18n/delivery_automatic_package.pot
odoo/addons/delivery_automatic_package/i18n/es.po
odoo/addons/delivery_automatic_package/i18n/it.po
odoo/addons/delivery_automatic_package/models/__init__.py
odoo/addons/delivery_automatic_package/models/delivery_carrier.py
odoo/addons/delivery_automatic_package/models/res_company.py
odoo/addons/delivery_automatic_package/models/res_config_settings.py
odoo/addons/delivery_automatic_package/models/stock_picking.py
odoo/addons/delivery_automatic_package/readme/CONFIGURE.rst
odoo/addons/delivery_automatic_package/readme/CONTRIBUTORS.rst
odoo/addons/delivery_automatic_package/readme/DESCRIPTION.rst
odoo/addons/delivery_automatic_package/static/description/icon.png
odoo/addons/delivery_automatic_package/static/description/index.html
odoo/addons/delivery_automatic_package/tests/__init__.py
odoo/addons/delivery_automatic_package/tests/test_automatic_package.py
odoo/addons/delivery_automatic_package/views/delivery_carrier.xml
odoo/addons/delivery_automatic_package/views/res_config_settings.xml
odoo_addon_delivery_automatic_package-16.0.1.0.0.7.dist-info/METADATA
odoo_addon_delivery_automatic_package-16.0.1.0.0.7.dist-info/WHEEL
odoo_addon_delivery_automatic_package-16.0.1.0.0.7.dist-info/top_level.txt
odoo_addon_delivery_automatic_package-16.0.1.0.0.7.dist-info/RECORD
